Metadata-Version: 2.1
Name: chinese-id-checker
Version: 0.9.2
Summary: chinese id checker
Home-page: https://github.com/BruceWW/chinese_id_checker
Author: Lin Luo / Bruce Liu
Author-email: 15869300264@163.com
License: UNKNOWN
Platform: any
Classifier: Programming Language :: Python :: 3.6
Classifier: Programming Language :: Python :: 3.7
Classifier: Programming Language :: Python :: 3.8
